{"treeAttributeDataMap":{"id":"root"},"type":"NORMAL","childs":[{"type":"SPACER","childs":[],"treeElementOpen":false},{"fragmentTypeDef":"Title","treeAttributeDataMap":{"colorAttribute":"red","id":"1","content":"1"},"type":"NORMAL","childs":[{"type":"SPACER","childs":[],"treeElementOpen":false},{"fragmentTypeDef":"Title","treeAttributeDataMap":{"colorAttribute":"blue","id":"311","content":"2314"},"type":"NORMAL","childs":[],"description":"311","treeElementOpen":true},{"type":"SPACER","childs":[],"treeElementOpen":false}],"description":"1","treeElementOpen":true},{"type":"SPACER","childs":[],"treeElementOpen":false}],"description":"root","treeElementOpen":true}